.gitignore
.travis.yml
CHANGES.txt
LICENSE.txt
MANIFEST.in
README.rst
setup.cfg
setup.py
tox.ini
hexagonit/__init__.py
hexagonit/__init__.pyc
hexagonit.recipe.cmmi.egg-info/PKG-INFO
hexagonit.recipe.cmmi.egg-info/SOURCES.txt
hexagonit.recipe.cmmi.egg-info/dependency_links.txt
hexagonit.recipe.cmmi.egg-info/entry_points.txt
hexagonit.recipe.cmmi.egg-info/namespace_packages.txt
hexagonit.recipe.cmmi.egg-info/not-zip-safe
hexagonit.recipe.cmmi.egg-info/requires.txt
hexagonit.recipe.cmmi.egg-info/top_level.txt
hexagonit/__pycache__/__init__.cpython-32.pyc
hexagonit/__pycache__/__init__.cpython-33.pyc
hexagonit/recipe/__init__.py
hexagonit/recipe/__init__.pyc
hexagonit/recipe/__pycache__/__init__.cpython-32.pyc
hexagonit/recipe/__pycache__/__init__.cpython-33.pyc
hexagonit/recipe/cmmi/README.txt
hexagonit/recipe/cmmi/__init__.py
hexagonit/recipe/cmmi/__init__.pyc
hexagonit/recipe/cmmi/tests.py
hexagonit/recipe/cmmi/tests.pyc
hexagonit/recipe/cmmi/testdata/Foo-Bar-0.0.0.tar.gz
hexagonit/recipe/cmmi/testdata/haproxy-1.4.8-dummy.tar.gz
hexagonit/recipe/cmmi/testdata/package-0.0.0.tar.gz