Metadata-Version: 1.1
Name: hexagonit.recipe.cmmi
Version: 2.0
Summary: zc.buildout recipe for compiling and installing source distributions.
Home-page: http://github.com/hexagonit/hexagonit.recipe.cmmi
Author: Kai Lautaportti
Author-email: kai.lautaportti@hexagonit.fi
License: BSD
Keywords: development buildout recipe
Platform: UNKNOWN
Classifier: Framework :: Buildout :: Recipe
Classifier: Framework :: Buildout
Classifier: Intended Audience :: Developers
Classifier: License :: OSI Approved :: BSD License
Classifier: Programming Language :: Python :: 2.6
Classifier: Programming Language :: Python :: 2.7
Classifier: Programming Language :: Python :: 3.2
Classifier: Programming Language :: Python :: 3.3
Classifier: Topic :: Software Development :: Build Tools
Classifier: Topic :: Software Development :: Libraries :: Python Modules
